genorm/__init__.py
genorm/algorithms.py
rna_genorm-0.1.0.dist-info/LICENSE
rna_genorm-0.1.0.dist-info/METADATA
rna_genorm-0.1.0.dist-info/WHEEL
rna_genorm-0.1.0.dist-info/top_level.txt
rna_genorm-0.1.0.dist-info/RECORD
