Metadata-Version: 2.1
Name: rna-genorm
Version: 0.1.0
Summary: Python implementation of the geNorm algorithm for gene expression.
Home-page: https://gitlab.com/hylkedonker/genorm
Author: H. C. Donker
Author-email: h.c.donker@umcg.nl
License: UNKNOWN
Project-URL: Bug Tracker, https://gitlab.com/hylkedonker/genorm/-/issues
Platform: UNKNOWN
Classifier: Programming Language :: Python :: 3
Classifier: License :: OSI Approved :: MIT License
Classifier: Operating System :: OS Independent
Requires-Python: >=3.9
License-File: LICENSE
